<?xml version="1.0" encoding="gb2312"?>
<root>
  <info value="0">
    <category>∏…∂π∏Ø</category>
    <money>62.7</money>
    <datetime>2012-12-19</datetime>
  </info>
  <info value="1">
    <category>÷ÌÃ„</category>
    <money>16.4</money>
    <datetime>2012-12-19</datetime>
  </info>
  <info value="2">
    <category>Õﬂπﬁº¶</category>
    <money>134.7</money>
    <datetime>2012-12-19</datetime>
  </info>
  <info value="3">
    <category>∫…“∂º¶</category>
    <money>236.5</money>
    <datetime>2012-12-19</datetime>
  </info>
  <info value="4">
    <category>º¶◊¶</category>
    <money>102.6</money>
    <datetime>2012-12-19</datetime>
  </info>
  <info value="5">
    <category>ŒÂª®»‚</category>
    <money>38.9</money>
    <datetime>2012-12-19</datetime>
  </info>
  <info value="6">
    <category>∫…“∂º¶</category>
    <money>300</money>
    <datetime>2012-12-20</datetime>
  </info>
  <info value="7">
    <category>Õﬂπﬁº¶</category>
    <money>249</money>
    <datetime>2012-12-20</datetime>
  </info>
  <info value="8">
    <category>ŒÂª®»‚</category>
    <money>33.6</money>
    <datetime>2012-12-20</datetime>
  </info>
  <info value="9">
    <category>÷Ì∏Œ</category>
    <money>37.5</money>
    <datetime>2012-12-20</datetime>
  </info>
  <info value="10">
    <category>º¶◊¶</category>
    <money>20</money>
    <datetime>2012-12-20</datetime>
  </info>
  <info value="11">
    <category>º¶Õ»</category>
    <money>60</money>
    <datetime>2012-12-20</datetime>
  </info>
  <info value="12">
    <category>—ºÕ»</category>
    <money>17.8</money>
    <datetime>2012-12-20</datetime>
  </info>
  <info value="13">
    <category>º¶≥·º‚</category>
    <money>33.7</money>
    <datetime>2012-12-20</datetime>
  </info>
  <info value="14">
    <category>—º◊”</category>
    <money>70.6</money>
    <datetime>2012-12-20</datetime>
  </info>
  <info value="15">
    <category>—ºÕ»</category>
    <money>15.4</money>
    <datetime>2012-12-20</datetime>
  </info>
  <info value="16">
    <category>∏…∂π∏Ø</category>
    <money>100.5</money>
    <datetime>2012-12-20</datetime>
  </info>
  <info value="17">
    <category>Õﬂπﬁº¶</category>
    <money>151.3</money>
    <datetime>2012-12-21</datetime>
  </info>
  <info value="18">
    <category>∫…“∂º¶</category>
    <money>214.3</money>
    <datetime>2012-12-21</datetime>
  </info>
  <info value="19">
    <category>∏…∂π∏Ø</category>
    <money>29.6</money>
    <datetime>2012-12-21</datetime>
  </info>
  <info value="20">
    <category>º¶Õ»</category>
    <money>52.1</money>
    <datetime>2012-12-21</datetime>
  </info>
  <info value="21">
    <category>º¶∏Œ</category>
    <money>23.2</money>
    <datetime>2012-12-21</datetime>
  </info>
  <info value="22">
    <category>ŒÂª®»‚</category>
    <money>36.5</money>
    <datetime>2012-12-21</datetime>
  </info>
  <info value="23">
    <category>—ºÕ»</category>
    <money>36.7</money>
    <datetime>2012-12-21</datetime>
  </info>
  <info value="24">
    <category>Õﬂπﬁº¶</category>
    <money>71.4</money>
    <datetime>2012-12-22</datetime>
  </info>
  <info value="25">
    <category>∫…“∂º¶</category>
    <money>184.6</money>
    <datetime>2012-12-22</datetime>
  </info>
  <info value="26">
    <category>º¶◊¶</category>
    <money>15.5</money>
    <datetime>2012-12-22</datetime>
  </info>
  <info value="27">
    <category>∏…∂π∏Ø</category>
    <money>48.8</money>
    <datetime>2012-12-22</datetime>
  </info>
  <info value="28">
    <category>—ºÕ»</category>
    <money>20.6</money>
    <datetime>2012-12-22</datetime>
  </info>
  <info value="29">
    <category>º¶Õ»</category>
    <money>25</money>
    <datetime>2012-12-22</datetime>
  </info>
  <info value="30">
    <category>º¶∂«</category>
    <money>4.5</money>
    <datetime>2012-12-22</datetime>
  </info>
  <info value="31">
    <category>÷Ì∏Œ</category>
    <money>18.2</money>
    <datetime>2012-12-22</datetime>
  </info>
  <info value="32">
    <category>ŒÂª®»‚</category>
    <money>35.4</money>
    <datetime>2012-12-22</datetime>
  </info>
  <info value="33">
    <category>Õﬂπﬁº¶</category>
    <money>47.1</money>
    <datetime>2012-12-24</datetime>
  </info>
  <info value="34">
    <category>∫…“∂º¶</category>
    <money>151.2</money>
    <datetime>2012-12-24</datetime>
  </info>
  <info value="35">
    <category>∏…∂π∏Ø</category>
    <money>46.7</money>
    <datetime>2012-12-24</datetime>
  </info>
  <info value="36">
    <category>º¶Õ»</category>
    <money>37.6</money>
    <datetime>2012-12-24</datetime>
  </info>
  <info value="37">
    <category>—º◊”</category>
    <money>24.6</money>
    <datetime>2012-12-24</datetime>
  </info>
  <info value="38">
    <category>º¶≥·º‚</category>
    <money>12.3</money>
    <datetime>2012-12-24</datetime>
  </info>
  <info value="39">
    <category>÷ÌÃ„</category>
    <money>59.3</money>
    <datetime>2012-12-24</datetime>
  </info>
  <info value="40">
    <category>∫…“∂º¶</category>
    <money>60.2</money>
    <datetime>2012-12-25</datetime>
  </info>
  <info value="41">
    <category>Õﬂπﬁº¶</category>
    <money>118.3</money>
    <datetime>2012-12-25</datetime>
  </info>
  <info value="42">
    <category>º¶Õ»</category>
    <money>41</money>
    <datetime>2012-12-25</datetime>
  </info>
  <info value="43">
    <category>º¶Õ»</category>
    <money>41</money>
    <datetime>2012-12-25</datetime>
  </info>
  <info value="44">
    <category>—ºÕ»</category>
    <money>28.3</money>
    <datetime>2012-12-25</datetime>
  </info>
  <info value="45">
    <category>º¶∏Œ</category>
    <money>7</money>
    <datetime>2012-12-25</datetime>
  </info>
  <info value="46">
    <category>º¶◊¶</category>
    <money>59.7</money>
    <datetime>2012-12-25</datetime>
  </info>
  <info value="47">
    <category>∏…∂π∏Ø</category>
    <money>40.8</money>
    <datetime>2012-12-25</datetime>
  </info>
  <info value="48">
    <category>÷ÌÃ„</category>
    <money>13.2</money>
    <datetime>2012-12-25</datetime>
  </info>
  <info value="49">
    <category>—º◊”</category>
    <money>14.9</money>
    <datetime>2012-12-25</datetime>
  </info>
  <info value="50">
    <category>ŒÂª®»‚</category>
    <money>11.8</money>
    <datetime>2012-12-25</datetime>
  </info>
  <info value="51">
    <category>∫…“∂º¶</category>
    <money>184.6</money>
    <datetime>2012-12-26</datetime>
  </info>
  <info value="52">
    <category>Õﬂπﬁº¶</category>
    <money>71.4</money>
    <datetime>2012-12-26</datetime>
  </info>
  <info value="53">
    <category>º¶Õ»</category>
    <money>25</money>
    <datetime>2012-12-26</datetime>
  </info>
  <info value="54">
    <category>—ºÕ»</category>
    <money>20.6</money>
    <datetime>2012-12-26</datetime>
  </info>
  <info value="55">
    <category>÷Ì∏Œ</category>
    <money>18.2</money>
    <datetime>2012-12-26</datetime>
  </info>
  <info value="56">
    <category>º¶∏Œ</category>
    <money>4.5</money>
    <datetime>2012-12-26</datetime>
  </info>
  <info value="57">
    <category>º¶◊¶</category>
    <money>15.5</money>
    <datetime>2012-12-26</datetime>
  </info>
  <info value="58">
    <category>∏…∂π∏Ø</category>
    <money>48.8</money>
    <datetime>2012-12-26</datetime>
  </info>
  <info value="59">
    <category>ŒÂª®»‚</category>
    <money>35.9</money>
    <datetime>2012-12-26</datetime>
  </info>
  <info value="60">
    <category>∫…“∂º¶</category>
    <money>149.1</money>
    <datetime>2012-12-27</datetime>
  </info>
  <info value="61">
    <category>Õﬂπﬁº¶</category>
    <money> 50</money>
    <datetime>2012-12-27</datetime>
  </info>
  <info value="62">
    <category>º¶Õ»</category>
    <money>30.2</money>
    <datetime>2012-12-27</datetime>
  </info>
  <info value="63">
    <category>—ºÕ»</category>
    <money>7.1</money>
    <datetime>2012-12-27</datetime>
  </info>
  <info value="64">
    <category>÷Ì∏Œ</category>
    <money>20.4</money>
    <datetime>2012-12-27</datetime>
  </info>
  <info value="65">
    <category>º¶≥·º‚</category>
    <money>4.9</money>
    <datetime>2012-12-27</datetime>
  </info>
  <info value="66">
    <category>º¶◊¶</category>
    <money>10.1</money>
    <datetime>2012-12-27</datetime>
  </info>
  <info value="67">
    <category>∏…∂π∏Ø</category>
    <money>18.1</money>
    <datetime>2012-12-27</datetime>
  </info>
  <info value="68">
    <category>÷ÌÃ„</category>
    <money>32.7</money>
    <datetime>2012-12-27</datetime>
  </info>
  <info value="69">
    <category>—º◊”</category>
    <money>18</money>
    <datetime>2012-12-27</datetime>
  </info>
  <info value="70">
    <category>∫…“∂º¶</category>
    <money>60.2</money>
    <datetime>2012-12-25</datetime>
  </info>
  <info value="71">
    <category>∫…“∂º¶</category>
    <money>269.5</money>
    <datetime>2012-12-28</datetime>
  </info>
  <info value="72">
    <category>Õﬂπﬁº¶</category>
    <money>75.4</money>
    <datetime>2012-12-28</datetime>
  </info>
  <info value="73">
    <category>º¶Õ»</category>
    <money>16.6</money>
    <datetime>2012-12-28</datetime>
  </info>
  <info value="74">
    <category>—ºÕ»</category>
    <money>42.2</money>
    <datetime>2012-12-28</datetime>
  </info>
  <info value="75">
    <category>÷Ì∏Œ</category>
    <money>9</money>
    <datetime>2012-12-28</datetime>
  </info>
  <info value="76">
    <category>º¶∏Œ</category>
    <money>21</money>
    <datetime>2012-12-28</datetime>
  </info>
  <info value="77">
    <category>º¶◊¶</category>
    <money>6.6</money>
    <datetime>2012-12-28</datetime>
  </info>
  <info value="78">
    <category>∏…∂π∏Ø</category>
    <money>60.04</money>
    <datetime>2012-12-28</datetime>
  </info>
  <info value="79">
    <category>∫…“∂º¶</category>
    <money>97.4</money>
    <datetime>2012-12-29</datetime>
  </info>
  <info value="80">
    <category>Õﬂπﬁº¶</category>
    <money>91.4</money>
    <datetime>2012-12-29</datetime>
  </info>
  <info value="81">
    <category>º¶Õ»</category>
    <money>7.6</money>
    <datetime>2012-12-29</datetime>
  </info>
  <info value="82">
    <category>º¶∏Œ</category>
    <money>4.1</money>
    <datetime>2012-12-29</datetime>
  </info>
  <info value="83">
    <category>∑ ≥¶</category>
    <money>21.9</money>
    <datetime>2012-12-29</datetime>
  </info>
  <info value="84">
    <category>÷Ì∂˙∂‰</category>
    <money>11</money>
    <datetime>2012-12-29</datetime>
  </info>
  <info value="85">
    <category>∏…∂π∏Ø</category>
    <money>23</money>
    <datetime>2012-12-29</datetime>
  </info>
  <info value="86">
    <category>∫…“∂º¶</category>
    <money>52.7</money>
    <datetime>2012-12-30</datetime>
  </info>
  <info value="87">
    <category>Õﬂπﬁº¶</category>
    <money>147.7</money>
    <datetime>2012-12-30</datetime>
  </info>
  <info value="88">
    <category>º¶Õ»</category>
    <money>33.8</money>
    <datetime>2012-12-30</datetime>
  </info>
  <info value="89">
    <category>º¶∏Œ</category>
    <money>28.6</money>
    <datetime>2012-12-30</datetime>
  </info>
  <info value="90">
    <category>º¶◊¶</category>
    <money>5.2</money>
    <datetime>2012-12-30</datetime>
  </info>
  <info value="91">
    <category>”„∆§</category>
    <money>5.4</money>
    <datetime>2012-12-30</datetime>
  </info>
  <info value="92">
    <category>÷ÌÕ∑»‚</category>
    <money>75.5</money>
    <datetime>2012-12-30</datetime>
  </info>
  <info value="93">
    <category>∑ ≥¶</category>
    <money>23.4</money>
    <datetime>2012-12-30</datetime>
  </info>
  <info value="94">
    <category>∏…∂π∏Ø</category>
    <money>65.1</money>
    <datetime>2012-12-30</datetime>
  </info>
  <info value="95">
    <category>÷ÌÃ„</category>
    <money>16.8</money>
    <datetime>2012-12-30</datetime>
  </info>
  <info value="96">
    <category>∫…“∂º¶</category>
    <money>182.8</money>
    <datetime>2012-12-31</datetime>
  </info>
  <info value="97">
    <category>Õﬂπﬁº¶</category>
    <money>252.3</money>
    <datetime>2012-12-31</datetime>
  </info>
  <info value="98">
    <category>º¶Õ»</category>
    <money>16.3</money>
    <datetime>2012-12-31</datetime>
  </info>
  <info value="99">
    <category>—ºÕ»</category>
    <money>14.2</money>
    <datetime>2012-12-31</datetime>
  </info>
  <info value="100">
    <category>÷Ì∏Œ</category>
    <money>47.5</money>
    <datetime>2012-12-31</datetime>
  </info>
  <info value="101">
    <category>º¶≥·º‚</category>
    <money>22.1</money>
    <datetime>2012-12-31</datetime>
  </info>
  <info value="102">
    <category>”„∆§</category>
    <money>2.6</money>
    <datetime>2012-12-31</datetime>
  </info>
  <info value="103">
    <category>÷ÌÕ∑»‚</category>
    <money>21.6</money>
    <datetime>2012-12-31</datetime>
  </info>
  <info value="104">
    <category>∑ ≥¶</category>
    <money>19.7</money>
    <datetime>2012-12-31</datetime>
  </info>
  <info value="105">
    <category>÷Ì∂˙∂‰</category>
    <money>10.9</money>
    <datetime>2012-12-31</datetime>
  </info>
  <info value="106">
    <category>¬Ì∞Â≥¶</category>
    <money>16.2</money>
    <datetime>2012-12-31</datetime>
  </info>
  <info value="107">
    <category>∏…∂π∏Ø</category>
    <money>34.5</money>
    <datetime>2012-12-31</datetime>
  </info>
  <info value="108">
    <category>—º◊”</category>
    <money>23.2</money>
    <datetime>2012-12-31</datetime>
  </info>
  <info value="109">
    <category>∫…“∂º¶</category>
    <money>774.9</money>
    <datetime>2013-01-01</datetime>
  </info>
  <info value="110">
    <category>Õﬂπﬁº¶</category>
    <money>590.8</money>
    <datetime>2013-01-01</datetime>
  </info>
  <info value="111">
    <category>º¶Õ»</category>
    <money>21.1</money>
    <datetime>2013-01-01</datetime>
  </info>
  <info value="112">
    <category>—ºÕ»</category>
    <money>42.1</money>
    <datetime>2013-01-01</datetime>
  </info>
  <info value="113">
    <category>÷Ì∏Œ</category>
    <money>192.9</money>
    <datetime>2013-01-01</datetime>
  </info>
  <info value="114">
    <category>º¶≥·º‚</category>
    <money>22.7</money>
    <datetime>2013-01-01</datetime>
  </info>
  <info value="115">
    <category>º¶◊¶</category>
    <money>28.8</money>
    <datetime>2013-01-01</datetime>
  </info>
  <info value="116">
    <category>¿±Àø</category>
    <money>18.7</money>
    <datetime>2013-01-01</datetime>
  </info>
  <info value="117">
    <category>”„∆§</category>
    <money>8.3</money>
    <datetime>2013-01-01</datetime>
  </info>
  <info value="118">
    <category>÷ÌÕ∑»‚</category>
    <money>350.1</money>
    <datetime>2013-01-01</datetime>
  </info>
  <info value="119">
    <category>∑ ≥¶</category>
    <money>42</money>
    <datetime>2013-01-01</datetime>
  </info>
  <info value="120">
    <category>÷Ì∂˙∂‰</category>
    <money>53.9</money>
    <datetime>2013-01-01</datetime>
  </info>
  <info value="121">
    <category>¬Ì∞Â≥¶</category>
    <money>22.2</money>
    <datetime>2013-01-01</datetime>
  </info>
  <info value="122">
    <category>∏…∂π∏Ø</category>
    <money>58.8</money>
    <datetime>2013-01-01</datetime>
  </info>
  <info value="123">
    <category>÷ÌÃ„</category>
    <money>122.2</money>
    <datetime>2013-01-01</datetime>
  </info>
  <info value="124">
    <category>—º◊”</category>
    <money>90.7</money>
    <datetime>2013-01-01</datetime>
  </info>
  <info value="125">
    <category>ŒÂª®»‚</category>
    <money>52.1</money>
    <datetime>2013-01-01</datetime>
  </info>
  <info value="126">
    <category>∫…“∂º¶</category>
    <money>248.5</money>
    <datetime>2013-01-02</datetime>
  </info>
  <info value="127">
    <category>Õﬂπﬁº¶</category>
    <money>275.9</money>
    <datetime>2013-01-02</datetime>
  </info>
  <info value="128">
    <category>÷Ì∏Œ</category>
    <money>22.4</money>
    <datetime>2013-01-02</datetime>
  </info>
  <info value="129">
    <category>”„∆§</category>
    <money>5.4</money>
    <datetime>2013-01-02</datetime>
  </info>
  <info value="130">
    <category>÷ÌÕ∑»‚</category>
    <money>78.3</money>
    <datetime>2013-01-02</datetime>
  </info>
  <info value="131">
    <category>∑ ≥¶</category>
    <money>54.3</money>
    <datetime>2013-01-02</datetime>
  </info>
  <info value="132">
    <category>÷Ì∂˙∂‰</category>
    <money>6.6</money>
    <datetime>2013-01-02</datetime>
  </info>
  <info value="133">
    <category>¬Ì∞Â≥¶</category>
    <money>15.3</money>
    <datetime>2013-01-02</datetime>
  </info>
  <info value="134">
    <category>∏…∂π∏Ø</category>
    <money>9.2</money>
    <datetime>2013-01-02</datetime>
  </info>
  <info value="135">
    <category>÷ÌÃ„</category>
    <money>34.2</money>
    <datetime>2013-01-02</datetime>
  </info>
  <info value="136">
    <category>—º◊”</category>
    <money>18.3</money>
    <datetime>2013-01-02</datetime>
  </info>
  <info value="137">
    <category>ŒÂª®»‚</category>
    <money>9.6</money>
    <datetime>2013-01-02</datetime>
  </info>
  <info value="138">
    <category>∫…“∂º¶</category>
    <money>88.2</money>
    <datetime>2013-01-03</datetime>
  </info>
  <info value="139">
    <category>Õﬂπﬁº¶</category>
    <money>51.7</money>
    <datetime>2013-01-03</datetime>
  </info>
  <info value="140">
    <category>÷Ì∏Œ</category>
    <money>65.9</money>
    <datetime>2013-01-03</datetime>
  </info>
  <info value="141">
    <category>”„∆§</category>
    <money>19.5</money>
    <datetime>2013-01-03</datetime>
  </info>
  <info value="142">
    <category>÷ÌÕ∑»‚</category>
    <money>67.7</money>
    <datetime>2013-01-03</datetime>
  </info>
  <info value="143">
    <category>¬Ì∞Â≥¶</category>
    <money>22.9</money>
    <datetime>2013-01-03</datetime>
  </info>
  <info value="144">
    <category>∏…∂π∏Ø</category>
    <money>25</money>
    <datetime>2013-01-03</datetime>
  </info>
  <info value="145">
    <category>∫£¥¯</category>
    <money>23.3</money>
    <datetime>2013-01-03</datetime>
  </info>
  <info value="146">
    <category>»‚∆§</category>
    <money>14.9</money>
    <datetime>2013-01-03</datetime>
  </info>
  <info value="147">
    <category> µµ∞</category>
    <money>5.6</money>
    <datetime>2013-01-03</datetime>
  </info>
  <info value="148">
    <category>∂«–ƒ</category>
    <money>11</money>
    <datetime>2013-01-03</datetime>
  </info>
  <info value="149">
    <category>÷Ì–ƒ</category>
    <money>14</money>
    <datetime>2013-01-03</datetime>
  </info>
  <info value="150">
    <category>∫…“∂º¶</category>
    <money>148.2</money>
    <datetime>2013-01-04</datetime>
  </info>
  <info value="151">
    <category>Õﬂπﬁº¶</category>
    <money>24.6</money>
    <datetime>2013-01-04</datetime>
  </info>
  <info value="152">
    <category>º¶Õ»</category>
    <money>12.6</money>
    <datetime>2013-01-04</datetime>
  </info>
  <info value="153">
    <category>—ºÕ»</category>
    <money>17.6</money>
    <datetime>2013-01-04</datetime>
  </info>
  <info value="154">
    <category>÷Ì∏Œ</category>
    <money>67.2</money>
    <datetime>2013-01-04</datetime>
  </info>
  <info value="155">
    <category>¿±Àø</category>
    <money>7.8</money>
    <datetime>2013-01-04</datetime>
  </info>
  <info value="156">
    <category>”„∆§</category>
    <money>16.7</money>
    <datetime>2013-01-04</datetime>
  </info>
  <info value="157">
    <category>÷ÌÕ∑»‚</category>
    <money>149.3</money>
    <datetime>2013-01-04</datetime>
  </info>
  <info value="158">
    <category>∏…∂π∏Ø</category>
    <money>17.1</money>
    <datetime>2013-01-04</datetime>
  </info>
  <info value="159">
    <category>÷ÌÃ„</category>
    <money>27.7</money>
    <datetime>2013-01-04</datetime>
  </info>
  <info value="160">
    <category>∫£¥¯</category>
    <money>13.9</money>
    <datetime>2013-01-04</datetime>
  </info>
  <info value="161">
    <category>∫…“∂º¶</category>
    <money>204.4</money>
    <datetime>2013-01-05</datetime>
  </info>
  <info value="162">
    <category>Õﬂπﬁº¶</category>
    <money>48.2</money>
    <datetime>2013-01-05</datetime>
  </info>
  <info value="163">
    <category>º¶Õ»</category>
    <money>23.3</money>
    <datetime>2013-01-05</datetime>
  </info>
  <info value="164">
    <category>÷Ì∏Œ</category>
    <money>41.4</money>
    <datetime>2013-01-05</datetime>
  </info>
  <info value="165">
    <category>º¶◊¶</category>
    <money>5.7</money>
    <datetime>2013-01-05</datetime>
  </info>
  <info value="166">
    <category>¿±Àø</category>
    <money>6.7</money>
    <datetime>2013-01-05</datetime>
  </info>
  <info value="167">
    <category>”„∆§</category>
    <money>8.2</money>
    <datetime>2013-01-05</datetime>
  </info>
  <info value="168">
    <category>÷ÌÕ∑»‚</category>
    <money>58.4</money>
    <datetime>2013-01-05</datetime>
  </info>
  <info value="169">
    <category>÷Ì∂˙∂‰</category>
    <money>7.7</money>
    <datetime>2013-01-05</datetime>
  </info>
  <info value="170">
    <category>∏…∂π∏Ø</category>
    <money>32.8</money>
    <datetime>2013-01-05</datetime>
  </info>
  <info value="171">
    <category>÷ÌÃ„</category>
    <money>16.3</money>
    <datetime>2013-01-05</datetime>
  </info>
  <info value="172">
    <category>—º◊”</category>
    <money>29</money>
    <datetime>2013-01-05</datetime>
  </info>
  <info value="173">
    <category>÷‚◊”</category>
    <money>130.8</money>
    <datetime>2013-01-05</datetime>
  </info>
  <info value="174">
    <category>—Ú—™</category>
    <money>15.9</money>
    <datetime>2013-01-05</datetime>
  </info>
  <info value="175">
    <category>∫£¥¯</category>
    <money>5</money>
    <datetime>2013-01-05</datetime>
  </info>
  <info value="176">
    <category>»‚∆§</category>
    <money>23.6</money>
    <datetime>2013-01-05</datetime>
  </info>
  <info value="177">
    <category>º¶≥·º‚</category>
    <money>11.4
</money>
    <datetime>2013-01-08</datetime>
  </info>
  <info value="178">
    <category>—Ú—™</category>
    <money>5.8</money>
    <datetime>2013-01-08</datetime>
  </info>
  <info value="179">
    <category>∏…∂π∏Ø</category>
    <money>37.3</money>
    <datetime>2013-01-07</datetime>
  </info>
  <info value="180">
    <category>»‚∆§</category>
    <money>10.4</money>
    <datetime>2013-01-07</datetime>
  </info>
  <info value="181">
    <category>∂«–ƒ</category>
    <money>19.3</money>
    <datetime>2013-01-07</datetime>
  </info>
  <info value="182">
    <category>∫…“∂º¶</category>
    <money>85.5</money>
    <datetime>2013-01-08</datetime>
  </info>
  <info value="183">
    <category>º¶Õ»</category>
    <money>10.6</money>
    <datetime>2013-01-08</datetime>
  </info>
  <info value="184">
    <category>Õﬂπﬁº¶</category>
    <money>72.7</money>
    <datetime>2013-01-08</datetime>
  </info>
  <info value="185">
    <category>÷Ì…‡Õ∑</category>
    <money>14.8</money>
    <datetime>2013-01-07</datetime>
  </info>
  <info value="186">
    <category>÷ÌÕ∑»‚</category>
    <money>20.3</money>
    <datetime>2013-01-07</datetime>
  </info>
  <info value="187">
    <category>÷Ì∂˙∂‰</category>
    <money>11.2</money>
    <datetime>2013-01-07</datetime>
  </info>
  <info value="188">
    <category>÷ÌÃ„</category>
    <money>16.8</money>
    <datetime>2013-01-07</datetime>
  </info>
  <info value="189">
    <category>÷Ì∏Œ</category>
    <money>35.1</money>
    <datetime>2013-01-07</datetime>
  </info>
  <info value="190">
    <category>—Ú—™</category>
    <money>11.2</money>
    <datetime>2013-01-07</datetime>
  </info>
  <info value="191">
    <category>—º◊”</category>
    <money>62.3</money>
    <datetime>2013-01-07</datetime>
  </info>
  <info value="192">
    <category>º¶Õ»</category>
    <money>18.3</money>
    <datetime>2013-01-07</datetime>
  </info>
  <info value="193">
    <category>∫£¥¯</category>
    <money>43.5</money>
    <datetime>2013-01-07</datetime>
  </info>
  <info value="194">
    <category>∫…“∂º¶</category>
    <money>354</money>
    <datetime>2013-01-06</datetime>
  </info>
  <info value="195">
    <category>Õﬂπﬁº¶</category>
    <money>69</money>
    <datetime>2013-01-06</datetime>
  </info>
  <info value="196">
    <category>—ºÕ»</category>
    <money>5.6</money>
    <datetime>2013-01-06</datetime>
  </info>
  <info value="197">
    <category>÷Ì∏Œ</category>
    <money>28.5</money>
    <datetime>2013-01-06</datetime>
  </info>
  <info value="198">
    <category>÷ÌÕ∑»‚</category>
    <money>16.3</money>
    <datetime>2013-01-06</datetime>
  </info>
  <info value="199">
    <category>∏…∂π∏Ø</category>
    <money>34.9</money>
    <datetime>2013-01-06</datetime>
  </info>
  <info value="200">
    <category>—Ú—™</category>
    <money>7.8</money>
    <datetime>2013-01-06</datetime>
  </info>
  <info value="201">
    <category>∫£¥¯</category>
    <money>50.3</money>
    <datetime>2013-01-06</datetime>
  </info>
  <info value="202">
    <category>»‚∆§</category>
    <money>13.9</money>
    <datetime>2013-01-06</datetime>
  </info>
  <info value="203">
    <category>ª§–ƒ</category>
    <money>13.2</money>
    <datetime>2013-01-06</datetime>
  </info>
  <info value="204">
    <category>Õﬂπﬁº¶</category>
    <money>100.2</money>
    <datetime>2013-01-07</datetime>
  </info>
  <info value="205">
    <category>∫…“∂º¶</category>
    <money>243.8</money>
    <datetime>2013-01-07</datetime>
  </info>
  <info value="206">
    <category>∫£¥¯</category>
    <money>14.6</money>
    <datetime>2013-01-08</datetime>
  </info>
  <info value="207">
    <category>—ºÕ»</category>
    <money>18.6</money>
    <datetime>2013-01-08</datetime>
  </info>
  <info value="208">
    <category>÷ÌÕ∑»‚</category>
    <money>32</money>
    <datetime>2013-01-08</datetime>
  </info>
  <info value="209">
    <category>÷Ì∏Œ</category>
    <money>11.5</money>
    <datetime>2013-01-08</datetime>
  </info>
  <info value="210">
    <category>∏…∂π∏Ø</category>
    <money>9.8</money>
    <datetime>2013-01-08</datetime>
  </info>
  <info value="211">
    <category>Õﬂπﬁº¶</category>
    <money>125.9</money>
    <datetime>2013-01-09</datetime>
  </info>
  <info value="212">
    <category>∫…“∂º¶</category>
    <money>167.4</money>
    <datetime>2013-01-09</datetime>
  </info>
  <info value="213">
    <category>º¶Õ»</category>
    <money>8.1
</money>
    <datetime>2013-01-09</datetime>
  </info>
  <info value="214">
    <category>º¶≥·º‚</category>
    <money>8.9
</money>
    <datetime>2013-01-09</datetime>
  </info>
  <info value="215">
    <category>∫£¥¯</category>
    <money>14.9
</money>
    <datetime>2013-01-09</datetime>
  </info>
  <info value="216">
    <category>÷‚◊”</category>
    <money>59.2
</money>
    <datetime>2013-01-09</datetime>
  </info>
  <info value="217">
    <category>—º◊”</category>
    <money>44.6</money>
    <datetime>2013-01-09</datetime>
  </info>
  <info value="218">
    <category>—ºÕ»</category>
    <money>11.6
</money>
    <datetime>2013-01-09</datetime>
  </info>
  <info value="219">
    <category>÷ÌÕ∑»‚</category>
    <money>21.3
</money>
    <datetime>2013-01-09</datetime>
  </info>
  <info value="220">
    <category>÷Ì∂˙∂‰</category>
    <money>16.3
</money>
    <datetime>2013-01-09</datetime>
  </info>
  <info value="221">
    <category>÷Ì∏Œ</category>
    <money>59.7
</money>
    <datetime>2013-01-09</datetime>
  </info>
  <info value="222">
    <category>∏…∂π∏Ø</category>
    <money>40.3
</money>
    <datetime>2013-01-09</datetime>
  </info>
  <info value="223">
    <category>¿±Àø</category>
    <money>4‘™
</money>
    <datetime>2013-01-09</datetime>
  </info>
  <info value="224">
    <category>Õﬂπﬁº¶</category>
    <money>77.7</money>
    <datetime>2013-01-10</datetime>
  </info>
  <info value="225">
    <category>∫…“∂º¶</category>
    <money>83.1</money>
    <datetime>2013-01-10</datetime>
  </info>
  <info value="226">
    <category>º¶Õ»</category>
    <money>39.4
</money>
    <datetime>2013-01-10</datetime>
  </info>
  <info value="227">
    <category>º¶◊¶</category>
    <money>6
</money>
    <datetime>2013-01-10</datetime>
  </info>
  <info value="228">
    <category>º¶≥·º‚</category>
    <money>5.1</money>
    <datetime>2013-01-10</datetime>
  </info>
  <info value="229">
    <category>∫£¥¯</category>
    <money>41.3
</money>
    <datetime>2013-01-10</datetime>
  </info>
  <info value="230">
    <category>—º◊”</category>
    <money>21.1</money>
    <datetime>2013-01-10</datetime>
  </info>
  <info value="231">
    <category>—Ú—™</category>
    <money>7.3</money>
    <datetime>2013-01-10</datetime>
  </info>
  <info value="232">
    <category>÷ÌÕ∑»‚</category>
    <money>13
</money>
    <datetime>2013-01-10</datetime>
  </info>
  <info value="233">
    <category>÷Ì∂˙∂‰</category>
    <money>19.4
</money>
    <datetime>2013-01-10</datetime>
  </info>
  <info value="234">
    <category>÷Ì∏Œ</category>
    <money>23.3
</money>
    <datetime>2013-01-10</datetime>
  </info>
  <info value="235">
    <category>∏…∂π∏Ø</category>
    <money>36.1</money>
    <datetime>2013-01-10</datetime>
  </info>
  <info value="236">
    <category>¿±Àø</category>
    <money>6
</money>
    <datetime>2013-01-10</datetime>
  </info>
  <info value="237">
    <category>ŒÂª®»‚</category>
    <money>7.3‘™
</money>
    <datetime>2013-01-10</datetime>
  </info>
</root>
